ipalint/__init__.py
ipalint/cli.py
ipalint/core.py
ipalint/ipa.py
ipalint/read.py
ipalint/report.py
ipalint/strnorm.py
ipalint/data/common_errors.tsv
ipalint/data/ipa.tsv
ipalint/tests/__init__.py
ipalint/tests/test_cli.py
ipalint/tests/test_ipa.py
ipalint/tests/test_read.py
ipalint/tests/test_report.py
ipalint/tests/test_strnorm.py
ipalint/tests/fixtures/hawaiian.csv
ipalint/tests/fixtures/hawaiian.tsv
ipalint/tests/fixtures/hawaiian.txt
ipalint-0.0.1.dist-info/DESCRIPTION.rst
ipalint-0.0.1.dist-info/METADATA
ipalint-0.0.1.dist-info/RECORD
ipalint-0.0.1.dist-info/WHEEL
ipalint-0.0.1.dist-info/entry_points.txt
ipalint-0.0.1.dist-info/metadata.json
ipalint-0.0.1.dist-info/top_level.txt
