Metadata-Version: 2.0
Name: ipalint
Version: 0.0.1
Summary: simple linter that checks datasets for IPA errors and inconsistencies
Home-page: https://github.com/pavelsof/ipalint
Author: Pavel Sofroniev
Author-email: pavelsof@gmail.com
License: MIT
Keywords: IPA lint
Platform: UNKNOWN
Classifier: Development Status :: 4 - Beta
Classifier: Environment :: Console
Classifier: Intended Audience :: Science/Research
Classifier: License :: OSI Approved :: MIT License
Classifier: Programming Language :: Python :: 3
Classifier: Programming Language :: Python :: 3 :: Only
Classifier: Topic :: Text Processing :: Linguistic
